rpds_py-0.23.0.dist-info/METADATA
rpds_py-0.23.0.dist-info/WHEEL
rpds_py-0.23.0.dist-info/licenses/LICENSE
rpds.libs/libgcc_s-1e52349c.so.1
rpds/__init__.py
rpds/__init__.pyi
rpds/py.typed
rpds/rpds.cpython-39-x86_64-linux-gnu.so
rpds_py-0.23.0.dist-info/RECORD
